odoo_tests_openerp_scripts-0.1.3.dist-info/top_level.txt
odoo_tests_openerp_scripts-0.1.3.dist-info/METADATA
odoo_tests_openerp_scripts-0.1.3.dist-info/DESCRIPTION.rst
odoo_tests_openerp_scripts-0.1.3.dist-info/entry_points.txt
odoo_tests_openerp_scripts-0.1.3.dist-info/WHEEL
odoo_tests_openerp_scripts-0.1.3.dist-info/RECORD
odoo_tests_openerp_scripts-0.1.3.dist-info/metadata.json
odoo_tests/odoo_tests.py
odoo_tests/__init__.py
