Metadata-Version: 2.0
Name: odoo-tests-openerp-scripts
Version: 0.1.3
Summary: Test openerp_scripts to be used with Anybox Odoo recipe.
Home-page: https://github.com/maxc0c0s/odoo_tests_openerp_scripts
Author: Sebastien Delisle
Author-email: seb0del@gmail.com
License: GNU GPL v3.0
Keywords: odoo_tests_openerp_scripts
Platform: UNKNOWN
Classifier: Development Status :: 2 - Pre-Alpha
Classifier: Intended Audience :: Developers
Classifier: License :: OSI Approved :: BSD License
Classifier: Natural Language :: English
Classifier: Framework :: Buildout :: Extension
Classifier: Programming Language :: Python :: 2
Classifier: Programming Language :: Python :: 2.6
Classifier: Programming Language :: Python :: 2.7
Requires-Dist: psycopg2 (==2.6)
Requires-Dist: argparse (==1.3.0)
